azure/mgmt/maintenance/__init__.py
azure/mgmt/maintenance/_configuration.py
azure/mgmt/maintenance/_maintenance_management_client.py
azure/mgmt/maintenance/_patch.py
azure/mgmt/maintenance/_serialization.py
azure/mgmt/maintenance/_vendor.py
azure/mgmt/maintenance/_version.py
azure/mgmt/maintenance/py.typed
azure/mgmt/maintenance/aio/__init__.py
azure/mgmt/maintenance/aio/_configuration.py
azure/mgmt/maintenance/aio/_maintenance_management_client.py
azure/mgmt/maintenance/aio/_patch.py
azure/mgmt/maintenance/aio/operations/__init__.py
azure/mgmt/maintenance/aio/operations/_apply_update_for_resource_group_operations.py
azure/mgmt/maintenance/aio/operations/_apply_updates_operations.py
azure/mgmt/maintenance/aio/operations/_configuration_assignments_for_resource_group_operations.py
azure/mgmt/maintenance/aio/operations/_configuration_assignments_for_subscriptions_operations.py
azure/mgmt/maintenance/aio/operations/_configuration_assignments_operations.py
azure/mgmt/maintenance/aio/operations/_configuration_assignments_within_subscription_operations.py
azure/mgmt/maintenance/aio/operations/_maintenance_configurations_for_resource_group_operations.py
azure/mgmt/maintenance/aio/operations/_maintenance_configurations_operations.py
azure/mgmt/maintenance/aio/operations/_operations.py
azure/mgmt/maintenance/aio/operations/_patch.py
azure/mgmt/maintenance/aio/operations/_public_maintenance_configurations_operations.py
azure/mgmt/maintenance/aio/operations/_updates_operations.py
azure/mgmt/maintenance/models/__init__.py
azure/mgmt/maintenance/models/_maintenance_management_client_enums.py
azure/mgmt/maintenance/models/_models_py3.py
azure/mgmt/maintenance/models/_patch.py
azure/mgmt/maintenance/operations/__init__.py
azure/mgmt/maintenance/operations/_apply_update_for_resource_group_operations.py
azure/mgmt/maintenance/operations/_apply_updates_operations.py
azure/mgmt/maintenance/operations/_configuration_assignments_for_resource_group_operations.py
azure_mgmt_maintenance-2.1.0.dist-info/LICENSE
azure_mgmt_maintenance-2.1.0.dist-info/METADATA
azure_mgmt_maintenance-2.1.0.dist-info/WHEEL
azure_mgmt_maintenance-2.1.0.dist-info/top_level.txt
azure_mgmt_maintenance-2.1.0.dist-info/RECORD
